vqu/__init__.py
vqu/cli.py
vqu/logger.py
vqu/models.py
vqu/project.py
vqu/yaml_file.py
vqu-0.1.3.dist-info/WHEEL
vqu-0.1.3.dist-info/entry_points.txt
vqu-0.1.3.dist-info/METADATA
vqu-0.1.3.dist-info/RECORD
