Metadata-Version: 2.3
Name: vqu
Version: 0.1.3
Summary: Query and update version numbers across multiple configuration files.
Keywords: version,dotenv,json,toml,xml,yaml,config,configuration,file,management,automation,project,projects,monorepo,cli
Author: Alexis Bergue
License: MIT License
Classifier: Development Status :: 3 - Alpha
Classifier: License :: OSI Approved :: MIT License
Classifier: Programming Language :: Python :: 3
Classifier: Programming Language :: Python :: 3.10
Classifier: Programming Language :: Python :: 3.11
Classifier: Programming Language :: Python :: 3.12
Classifier: Programming Language :: Python :: 3.13
Classifier: Programming Language :: Python :: 3.14
Classifier: Operating System :: MacOS :: MacOS X
Classifier: Operating System :: Microsoft :: Windows
Classifier: Operating System :: POSIX
Classifier: Topic :: Software Development
Classifier: Topic :: Software Development :: Build Tools
Classifier: Topic :: Utilities
Requires-Dist: docker>=7.1.0
Requires-Dist: pydantic>=2.12.5
Requires-Dist: pyyaml>=6.0.3
Requires-Dist: termcolor>=3.2.0
Requires-Python: >=3.10
Project-URL: Issues, https://github.com/alexisbg/vqu/issues
Project-URL: Repository, https://github.com/alexisbg/vqu
